djang_wechat/__init__.py
djang_wechat/apps.py
djang_wechat/common.py
djang_wechat/models.py
djang_wechat/msg_admin.py
djang_wechat/tag_admin.py
djang_wechat/migrations/0001_initial.py
djang_wechat/migrations/__init__.py
django_wechat_common-0.6.dist-info/METADATA
django_wechat_common-0.6.dist-info/WHEEL
django_wechat_common-0.6.dist-info/top_level.txt
django_wechat_common-0.6.dist-info/RECORD
