Metadata-Version: 2.1
Name: django-wechat-common
Version: 0.6
Summary: Django wx
Home-page: UNKNOWN
Author: yangcheng
Author-email: yangcheng.fan@yuemia.com
License: MIT
Platform: UNKNOWN
